minipy3/__init__.py
minipy3/__main__.py
minipy3/semicolon.py
minipy3-1.0.0.dist-info/LICENSE
minipy3-1.0.0.dist-info/METADATA
minipy3-1.0.0.dist-info/WHEEL
minipy3-1.0.0.dist-info/top_level.txt
minipy3-1.0.0.dist-info/RECORD
