Metadata-Version: 2.1
Name: minipy3
Version: 1.0.0
Summary: Minimizes Python3 code
Home-page: UNKNOWN
Author: Nikita (NIKDISSV)
Author-email: nikdissv@proton.me
License: MIT
Project-URL: GitHub, https://github.com/NIKDISSV-Forever/minipy3
Keywords: minipy,minimize,code,.min.py,compress
Platform: UNKNOWN
Classifier: Development Status :: 4 - Beta
Classifier: Intended Audience :: Developers
Classifier: Operating System :: OS Independent
Classifier: Programming Language :: Python :: 3
Classifier: Environment :: Console
Classifier: Topic :: Software Development :: Code Generators
Classifier: Topic :: System :: Archiving :: Compression
Classifier: License :: OSI Approved
Classifier: License :: OSI Approved :: MIT License
Requires-Python: >=3.9
License-File: LICENSE
